{
  "format": "alignment",
  "version": "0.4",
  "type": "audio-reference",
  "roles": [
    "timecode",
    "text-reference"
  ],
  "groups": [
    {
      "documents": [
        {
          "scheme": "vtt-timecode",
          "docid": "https://cdn.aquifer.bible/aquifer-content/scripture/SWH/OKCV/audio/mp3/SWH_OKCV_008_RUT_001.mp3"
        },
        {
          "scheme": "u23003"
        }
      ],
      "records": [
        {
          "references": [
            [
              "000:00:05.880 --> 000:00:23.200"
            ],
            [
              "RUT 1:1"
            ]
          ]
        },
        {
          "references": [
            [
              "000:00:23.200 --> 000:00:41.320"
            ],
            [
              "RUT 1:2"
            ]
          ]
        },
        {
          "references": [
            [
              "000:00:41.320 --> 000:00:48.400"
            ],
            [
              "RUT 1:3"
            ]
          ]
        },
        {
          "references": [
            [
              "000:00:48.400 --> 000:00:57.700"
            ],
            [
              "RUT 1:4"
            ]
          ]
        },
        {
          "references": [
            [
              "000:00:57.700 --> 000:01:05.460"
            ],
            [
              "RUT 1:5"
            ]
          ]
        },
        {
          "references": [
            [
              "000:01:05.460 --> 000:01:16.340"
            ],
            [
              "RUT 1:6"
            ]
          ]
        },
        {
          "references": [
            [
              "000:01:16.340 --> 000:01:24.180"
            ],
            [
              "RUT 1:7"
            ]
          ]
        },
        {
          "references": [
            [
              "000:01:24.180 --> 000:01:39.560"
            ],
            [
              "RUT 1:8"
            ]
          ]
        },
        {
          "references": [
            [
              "000:01:39.560 --> 000:01:49.780"
            ],
            [
              "RUT 1:9"
            ]
          ]
        },
        {
          "references": [
            [
              "000:01:49.780 --> 000:01:54.960"
            ],
            [
              "RUT 1:10"
            ]
          ]
        },
        {
          "references": [
            [
              "000:01:54.960 --> 000:02:07.860"
            ],
            [
              "RUT 1:11"
            ]
          ]
        },
        {
          "references": [
            [
              "000:02:07.860 --> 000:02:25.120"
            ],
            [
              "RUT 1:12"
            ]
          ]
        },
        {
          "references": [
            [
              "000:02:25.120 --> 000:02:42.840"
            ],
            [
              "RUT 1:13"
            ]
          ]
        },
        {
          "references": [
            [
              "000:02:42.840 --> 000:02:55.760"
            ],
            [
              "RUT 1:14"
            ]
          ]
        },
        {
          "references": [
            [
              "000:02:55.760 --> 000:03:04.660"
            ],
            [
              "RUT 1:15"
            ]
          ]
        },
        {
          "references": [
            [
              "000:03:04.660 --> 000:03:24.200"
            ],
            [
              "RUT 1:16"
            ]
          ]
        },
        {
          "references": [
            [
              "000:03:24.200 --> 000:03:39.660"
            ],
            [
              "RUT 1:17"
            ]
          ]
        },
        {
          "references": [
            [
              "000:03:39.660 --> 000:03:47.460"
            ],
            [
              "RUT 1:18"
            ]
          ]
        },
        {
          "references": [
            [
              "000:03:47.460 --> 000:04:03.160"
            ],
            [
              "RUT 1:19"
            ]
          ]
        },
        {
          "references": [
            [
              "000:04:03.160 --> 000:04:15.180"
            ],
            [
              "RUT 1:20"
            ]
          ]
        },
        {
          "references": [
            [
              "000:04:15.180 --> 000:04:30.260"
            ],
            [
              "RUT 1:21"
            ]
          ]
        },
        {
          "references": [
            [
              "000:04:30.260 --> 000:04:41.160"
            ],
            [
              "RUT 1:22"
            ]
          ]
        }
      ]
    },
    {
      "documents": [
        {
          "scheme": "vtt-timecode",
          "docid": "https://cdn.aquifer.bible/aquifer-content/scripture/SWH/OKCV/audio/mp3/SWH_OKCV_008_RUT_002.mp3"
        },
        {
          "scheme": "u23003"
        }
      ],
      "records": [
        {
          "references": [
            [
              "000:00:03.680 --> 000:00:12.480"
            ],
            [
              "RUT 2:1"
            ]
          ]
        },
        {
          "references": [
            [
              "000:00:12.480 --> 000:00:27.400"
            ],
            [
              "RUT 2:2"
            ]
          ]
        },
        {
          "references": [
            [
              "000:00:27.400 --> 000:00:42.360"
            ],
            [
              "RUT 2:3"
            ]
          ]
        },
        {
          "references": [
            [
              "000:00:42.360 --> 000:00:54.980"
            ],
            [
              "RUT 2:4"
            ]
          ]
        },
        {
          "references": [
            [
              "000:00:54.980 --> 000:01:02.140"
            ],
            [
              "RUT 2:5"
            ]
          ]
        },
        {
          "references": [
            [
              "000:01:02.140 --> 000:01:11.220"
            ],
            [
              "RUT 2:6"
            ]
          ]
        },
        {
          "references": [
            [
              "000:01:11.220 --> 000:01:27.660"
            ],
            [
              "RUT 2:7"
            ]
          ]
        },
        {
          "references": [
            [
              "000:01:27.660 --> 000:01:43.260"
            ],
            [
              "RUT 2:8"
            ]
          ]
        },
        {
          "references": [
            [
              "000:01:43.260 --> 000:01:58.740"
            ],
            [
              "RUT 2:9"
            ]
          ]
        },
        {
          "references": [
            [
              "000:01:58.740 --> 000:02:10.880"
            ],
            [
              "RUT 2:10"
            ]
          ]
        },
        {
          "references": [
            [
              "000:02:10.880 --> 000:02:28.860"
            ],
            [
              "RUT 2:11"
            ]
          ]
        },
        {
          "references": [
            [
              "000:02:28.860 --> 000:02:39.420"
            ],
            [
              "RUT 2:12"
            ]
          ]
        },
        {
          "references": [
            [
              "000:02:39.420 --> 000:02:57.760"
            ],
            [
              "RUT 2:13"
            ]
          ]
        },
        {
          "references": [
            [
              "000:02:57.760 --> 000:03:16.120"
            ],
            [
              "RUT 2:14"
            ]
          ]
        },
        {
          "references": [
            [
              "000:03:16.120 --> 000:03:26.660"
            ],
            [
              "RUT 2:15"
            ]
          ]
        },
        {
          "references": [
            [
              "000:03:26.660 --> 000:03:33.880"
            ],
            [
              "RUT 2:16"
            ]
          ]
        },
        {
          "references": [
            [
              "000:03:33.880 --> 000:03:42.720"
            ],
            [
              "RUT 2:17"
            ]
          ]
        },
        {
          "references": [
            [
              "000:03:42.720 --> 000:03:56.840"
            ],
            [
              "RUT 2:18"
            ]
          ]
        },
        {
          "references": [
            [
              "000:03:56.840 --> 000:04:22.920"
            ],
            [
              "RUT 2:19"
            ]
          ]
        },
        {
          "references": [
            [
              "000:04:22.920 --> 000:04:41.800"
            ],
            [
              "RUT 2:20"
            ]
          ]
        },
        {
          "references": [
            [
              "000:04:41.800 --> 000:04:52.740"
            ],
            [
              "RUT 2:21"
            ]
          ]
        },
        {
          "references": [
            [
              "000:04:52.740 --> 000:05:05.480"
            ],
            [
              "RUT 2:22"
            ]
          ]
        },
        {
          "references": [
            [
              "000:05:05.480 --> 000:05:17.360"
            ],
            [
              "RUT 2:23"
            ]
          ]
        }
      ]
    },
    {
      "documents": [
        {
          "scheme": "vtt-timecode",
          "docid": "https://cdn.aquifer.bible/aquifer-content/scripture/SWH/OKCV/audio/mp3/SWH_OKCV_008_RUT_003.mp3"
        },
        {
          "scheme": "u23003"
        }
      ],
      "records": [
        {
          "references": [
            [
              "000:00:03.680 --> 000:00:14.140"
            ],
            [
              "RUT 3:1"
            ]
          ]
        },
        {
          "references": [
            [
              "000:00:14.140 --> 000:00:27.060"
            ],
            [
              "RUT 3:2"
            ]
          ]
        },
        {
          "references": [
            [
              "000:00:27.060 --> 000:00:43.380"
            ],
            [
              "RUT 3:3"
            ]
          ]
        },
        {
          "references": [
            [
              "000:00:43.380 --> 000:00:55.380"
            ],
            [
              "RUT 3:4"
            ]
          ]
        },
        {
          "references": [
            [
              "000:00:55.380 --> 000:01:00.840"
            ],
            [
              "RUT 3:5"
            ]
          ]
        },
        {
          "references": [
            [
              "000:01:00.840 --> 000:01:09.820"
            ],
            [
              "RUT 3:6"
            ]
          ]
        },
        {
          "references": [
            [
              "000:01:09.820 --> 000:01:25.900"
            ],
            [
              "RUT 3:7"
            ]
          ]
        },
        {
          "references": [
            [
              "000:01:25.900 --> 000:01:34.700"
            ],
            [
              "RUT 3:8"
            ]
          ]
        },
        {
          "references": [
            [
              "000:01:34.700 --> 000:01:48.700"
            ],
            [
              "RUT 3:9"
            ]
          ]
        },
        {
          "references": [
            [
              "000:01:48.700 --> 000:02:04.260"
            ],
            [
              "RUT 3:10"
            ]
          ]
        },
        {
          "references": [
            [
              "000:02:04.260 --> 000:02:17.820"
            ],
            [
              "RUT 3:11"
            ]
          ]
        },
        {
          "references": [
            [
              "000:02:17.820 --> 000:02:27.780"
            ],
            [
              "RUT 3:12"
            ]
          ]
        },
        {
          "references": [
            [
              "000:02:27.780 --> 000:02:44.260"
            ],
            [
              "RUT 3:13"
            ]
          ]
        },
        {
          "references": [
            [
              "000:02:44.260 --> 000:03:00.940"
            ],
            [
              "RUT 3:14"
            ]
          ]
        },
        {
          "references": [
            [
              "000:03:00.940 --> 000:03:15.480"
            ],
            [
              "RUT 3:15"
            ]
          ]
        },
        {
          "references": [
            [
              "000:03:15.480 --> 000:03:28.300"
            ],
            [
              "RUT 3:16"
            ]
          ]
        },
        {
          "references": [
            [
              "000:03:28.300 --> 000:03:38.060"
            ],
            [
              "RUT 3:17"
            ]
          ]
        },
        {
          "references": [
            [
              "000:03:38.060 --> 000:03:52.080"
            ],
            [
              "RUT 3:18"
            ]
          ]
        }
      ]
    },
    {
      "documents": [
        {
          "scheme": "vtt-timecode",
          "docid": "https://cdn.aquifer.bible/aquifer-content/scripture/SWH/OKCV/audio/mp3/SWH_OKCV_008_RUT_004.mp3"
        },
        {
          "scheme": "u23003"
        }
      ],
      "records": [
        {
          "references": [
            [
              "000:00:03.680 --> 000:00:24.520"
            ],
            [
              "RUT 4:1"
            ]
          ]
        },
        {
          "references": [
            [
              "000:00:24.520 --> 000:00:34.540"
            ],
            [
              "RUT 4:2"
            ]
          ]
        },
        {
          "references": [
            [
              "000:00:34.540 --> 000:00:48.180"
            ],
            [
              "RUT 4:3"
            ]
          ]
        },
        {
          "references": [
            [
              "000:00:48.180 --> 000:01:18.760"
            ],
            [
              "RUT 4:4"
            ]
          ]
        },
        {
          "references": [
            [
              "000:01:18.760 --> 000:01:32.840"
            ],
            [
              "RUT 4:5"
            ]
          ]
        },
        {
          "references": [
            [
              "000:01:32.840 --> 000:01:49.020"
            ],
            [
              "RUT 4:6"
            ]
          ]
        },
        {
          "references": [
            [
              "000:01:49.020 --> 000:02:04.600"
            ],
            [
              "RUT 4:7"
            ]
          ]
        },
        {
          "references": [
            [
              "000:02:04.600 --> 000:02:14.460"
            ],
            [
              "RUT 4:8"
            ]
          ]
        },
        {
          "references": [
            [
              "000:02:14.460 --> 000:02:30.720"
            ],
            [
              "RUT 4:9"
            ]
          ]
        },
        {
          "references": [
            [
              "000:02:30.720 --> 000:02:51.420"
            ],
            [
              "RUT 4:10"
            ]
          ]
        },
        {
          "references": [
            [
              "000:02:51.420 --> 000:03:17.740"
            ],
            [
              "RUT 4:11"
            ]
          ]
        },
        {
          "references": [
            [
              "000:03:17.740 --> 000:03:30.460"
            ],
            [
              "RUT 4:12"
            ]
          ]
        },
        {
          "references": [
            [
              "000:03:30.460 --> 000:03:44.080"
            ],
            [
              "RUT 4:13"
            ]
          ]
        },
        {
          "references": [
            [
              "000:03:44.080 --> 000:03:56.120"
            ],
            [
              "RUT 4:14"
            ]
          ]
        },
        {
          "references": [
            [
              "000:03:56.120 --> 000:04:10.940"
            ],
            [
              "RUT 4:15"
            ]
          ]
        },
        {
          "references": [
            [
              "000:04:10.940 --> 000:04:17.000"
            ],
            [
              "RUT 4:16"
            ]
          ]
        },
        {
          "references": [
            [
              "000:04:17.000 --> 000:04:31.820"
            ],
            [
              "RUT 4:17"
            ]
          ]
        },
        {
          "references": [
            [
              "000:04:31.820 --> 000:04:38.060"
            ],
            [
              "RUT 4:18"
            ]
          ]
        },
        {
          "references": [
            [
              "000:04:38.060 --> 000:04:43.600"
            ],
            [
              "RUT 4:19"
            ]
          ]
        },
        {
          "references": [
            [
              "000:04:43.600 --> 000:04:49.840"
            ],
            [
              "RUT 4:20"
            ]
          ]
        },
        {
          "references": [
            [
              "000:04:49.840 --> 000:04:55.420"
            ],
            [
              "RUT 4:21"
            ]
          ]
        },
        {
          "references": [
            [
              "000:04:55.420 --> 000:05:01.400"
            ],
            [
              "RUT 4:22"
            ]
          ]
        }
      ]
    }
  ]
}