{
  "format": "alignment",
  "version": "0.4",
  "type": "audio-reference",
  "roles": [
    "timecode",
    "text-reference"
  ],
  "groups": [
    {
      "documents": [
        {
          "scheme": "vtt-timecode",
          "docid": "https://cdn.aquifer.bible/aquifer-content/scripture/SWH/OKCV/audio/mp3/SWH_OKCV_029_JOL_001.mp3"
        },
        {
          "scheme": "u23003"
        }
      ],
      "records": [
        {
          "references": [
            [
              "000:00:05.880 --> 000:00:10.380"
            ],
            [
              "JOL 1:1"
            ]
          ]
        },
        {
          "references": [
            [
              "000:00:10.380 --> 000:00:26.020"
            ],
            [
              "JOL 1:2"
            ]
          ]
        },
        {
          "references": [
            [
              "000:00:26.020 --> 000:00:36.100"
            ],
            [
              "JOL 1:3"
            ]
          ]
        },
        {
          "references": [
            [
              "000:00:36.100 --> 000:00:49.780"
            ],
            [
              "JOL 1:4"
            ]
          ]
        },
        {
          "references": [
            [
              "000:00:49.780 --> 000:01:05.720"
            ],
            [
              "JOL 1:5"
            ]
          ]
        },
        {
          "references": [
            [
              "000:01:05.720 --> 000:01:16.900"
            ],
            [
              "JOL 1:6"
            ]
          ]
        },
        {
          "references": [
            [
              "000:01:16.900 --> 000:01:29.260"
            ],
            [
              "JOL 1:7"
            ]
          ]
        },
        {
          "references": [
            [
              "000:01:29.260 --> 000:01:37.360"
            ],
            [
              "JOL 1:8"
            ]
          ]
        },
        {
          "references": [
            [
              "000:01:37.360 --> 000:01:50.160"
            ],
            [
              "JOL 1:9"
            ]
          ]
        },
        {
          "references": [
            [
              "000:01:50.160 --> 000:02:01.960"
            ],
            [
              "JOL 1:10"
            ]
          ]
        },
        {
          "references": [
            [
              "000:02:01.960 --> 000:02:17.280"
            ],
            [
              "JOL 1:11"
            ]
          ]
        },
        {
          "references": [
            [
              "000:02:17.280 --> 000:02:33.680"
            ],
            [
              "JOL 1:12"
            ]
          ]
        },
        {
          "references": [
            [
              "000:02:33.680 --> 000:03:00.460"
            ],
            [
              "JOL 1:13"
            ]
          ]
        },
        {
          "references": [
            [
              "000:03:00.460 --> 000:03:17.600"
            ],
            [
              "JOL 1:14"
            ]
          ]
        },
        {
          "references": [
            [
              "000:03:17.600 --> 000:03:27.520"
            ],
            [
              "JOL 1:15"
            ]
          ]
        },
        {
          "references": [
            [
              "000:03:27.520 --> 000:03:36.680"
            ],
            [
              "JOL 1:16"
            ]
          ]
        },
        {
          "references": [
            [
              "000:03:36.680 --> 000:03:50.920"
            ],
            [
              "JOL 1:17"
            ]
          ]
        },
        {
          "references": [
            [
              "000:03:50.920 --> 000:04:04.000"
            ],
            [
              "JOL 1:18"
            ]
          ]
        },
        {
          "references": [
            [
              "000:04:04.000 --> 000:04:14.260"
            ],
            [
              "JOL 1:19"
            ]
          ]
        },
        {
          "references": [
            [
              "000:04:14.260 --> 000:04:26.600"
            ],
            [
              "JOL 1:20"
            ]
          ]
        }
      ]
    },
    {
      "documents": [
        {
          "scheme": "vtt-timecode",
          "docid": "https://cdn.aquifer.bible/aquifer-content/scripture/SWH/OKCV/audio/mp3/SWH_OKCV_029_JOL_002.mp3"
        },
        {
          "scheme": "u23003"
        }
      ],
      "records": [
        {
          "references": [
            [
              "000:00:03.680 --> 000:00:18.140"
            ],
            [
              "JOL 2:1"
            ]
          ]
        },
        {
          "references": [
            [
              "000:00:18.140 --> 000:00:43.760"
            ],
            [
              "JOL 2:2"
            ]
          ]
        },
        {
          "references": [
            [
              "000:00:43.760 --> 000:01:01.180"
            ],
            [
              "JOL 2:3"
            ]
          ]
        },
        {
          "references": [
            [
              "000:01:01.180 --> 000:01:09.440"
            ],
            [
              "JOL 2:4"
            ]
          ]
        },
        {
          "references": [
            [
              "000:01:09.440 --> 000:01:25.060"
            ],
            [
              "JOL 2:5"
            ]
          ]
        },
        {
          "references": [
            [
              "000:01:25.060 --> 000:01:34.240"
            ],
            [
              "JOL 2:6"
            ]
          ]
        },
        {
          "references": [
            [
              "000:01:34.240 --> 000:01:47.280"
            ],
            [
              "JOL 2:7"
            ]
          ]
        },
        {
          "references": [
            [
              "000:01:47.280 --> 000:02:00.600"
            ],
            [
              "JOL 2:8"
            ]
          ]
        },
        {
          "references": [
            [
              "000:02:00.600 --> 000:02:11.300"
            ],
            [
              "JOL 2:9"
            ]
          ]
        },
        {
          "references": [
            [
              "000:02:11.300 --> 000:02:24.660"
            ],
            [
              "JOL 2:10"
            ]
          ]
        },
        {
          "references": [
            [
              "000:02:24.660 --> 000:02:45.020"
            ],
            [
              "JOL 2:11"
            ]
          ]
        },
        {
          "references": [
            [
              "000:02:45.020 --> 000:02:55.140"
            ],
            [
              "JOL 2:12"
            ]
          ]
        },
        {
          "references": [
            [
              "000:02:55.140 --> 000:03:17.380"
            ],
            [
              "JOL 2:13"
            ]
          ]
        },
        {
          "references": [
            [
              "000:03:17.380 --> 000:03:32.200"
            ],
            [
              "JOL 2:14"
            ]
          ]
        },
        {
          "references": [
            [
              "000:03:32.200 --> 000:03:42.540"
            ],
            [
              "JOL 2:15"
            ]
          ]
        },
        {
          "references": [
            [
              "000:03:42.540 --> 000:04:04.140"
            ],
            [
              "JOL 2:16"
            ]
          ]
        },
        {
          "references": [
            [
              "000:04:04.140 --> 000:04:30.080"
            ],
            [
              "JOL 2:17"
            ]
          ]
        },
        {
          "references": [
            [
              "000:04:30.080 --> 000:04:37.380"
            ],
            [
              "JOL 2:18"
            ]
          ]
        },
        {
          "references": [
            [
              "000:04:37.380 --> 000:04:55.220"
            ],
            [
              "JOL 2:19"
            ]
          ]
        },
        {
          "references": [
            [
              "000:04:55.220 --> 000:05:24.840"
            ],
            [
              "JOL 2:20"
            ]
          ]
        },
        {
          "references": [
            [
              "000:05:24.840 --> 000:05:33.420"
            ],
            [
              "JOL 2:21"
            ]
          ]
        },
        {
          "references": [
            [
              "000:05:33.420 --> 000:05:45.540"
            ],
            [
              "JOL 2:22"
            ]
          ]
        },
        {
          "references": [
            [
              "000:05:45.540 --> 000:06:02.100"
            ],
            [
              "JOL 2:23"
            ]
          ]
        },
        {
          "references": [
            [
              "000:06:02.100 --> 000:06:11.380"
            ],
            [
              "JOL 2:24"
            ]
          ]
        },
        {
          "references": [
            [
              "000:06:11.380 --> 000:06:24.600"
            ],
            [
              "JOL 2:25"
            ]
          ]
        },
        {
          "references": [
            [
              "000:06:24.600 --> 000:06:37.780"
            ],
            [
              "JOL 2:26"
            ]
          ]
        },
        {
          "references": [
            [
              "000:06:37.780 --> 000:06:51.700"
            ],
            [
              "JOL 2:27"
            ]
          ]
        },
        {
          "references": [
            [
              "000:06:51.700 --> 000:07:07.080"
            ],
            [
              "JOL 2:28"
            ]
          ]
        },
        {
          "references": [
            [
              "000:07:07.080 --> 000:07:15.180"
            ],
            [
              "JOL 2:29"
            ]
          ]
        },
        {
          "references": [
            [
              "000:07:15.180 --> 000:07:27.380"
            ],
            [
              "JOL 2:30"
            ]
          ]
        },
        {
          "references": [
            [
              "000:07:27.380 --> 000:07:37.920"
            ],
            [
              "JOL 2:31"
            ]
          ]
        },
        {
          "references": [
            [
              "000:07:37.920 --> 000:07:57.360"
            ],
            [
              "JOL 2:32"
            ]
          ]
        }
      ]
    },
    {
      "documents": [
        {
          "scheme": "vtt-timecode",
          "docid": "https://cdn.aquifer.bible/aquifer-content/scripture/SWH/OKCV/audio/mp3/SWH_OKCV_029_JOL_003.mp3"
        },
        {
          "scheme": "u23003"
        }
      ],
      "records": [
        {
          "references": [
            [
              "000:00:03.680 --> 000:00:10.060"
            ],
            [
              "JOL 3:1"
            ]
          ]
        },
        {
          "references": [
            [
              "000:00:10.060 --> 000:00:30.960"
            ],
            [
              "JOL 3:2"
            ]
          ]
        },
        {
          "references": [
            [
              "000:00:30.960 --> 000:00:41.080"
            ],
            [
              "JOL 3:3"
            ]
          ]
        },
        {
          "references": [
            [
              "000:00:41.080 --> 000:01:03.240"
            ],
            [
              "JOL 3:4"
            ]
          ]
        },
        {
          "references": [
            [
              "000:01:03.240 --> 000:01:11.160"
            ],
            [
              "JOL 3:5"
            ]
          ]
        },
        {
          "references": [
            [
              "000:01:11.160 --> 000:01:18.900"
            ],
            [
              "JOL 3:6"
            ]
          ]
        },
        {
          "references": [
            [
              "000:01:18.900 --> 000:01:29.780"
            ],
            [
              "JOL 3:7"
            ]
          ]
        },
        {
          "references": [
            [
              "000:01:29.780 --> 000:01:42.600"
            ],
            [
              "JOL 3:8"
            ]
          ]
        },
        {
          "references": [
            [
              "000:01:42.600 --> 000:01:57.180"
            ],
            [
              "JOL 3:9"
            ]
          ]
        },
        {
          "references": [
            [
              "000:01:57.180 --> 000:02:08.980"
            ],
            [
              "JOL 3:10"
            ]
          ]
        },
        {
          "references": [
            [
              "000:02:08.980 --> 000:02:20.960"
            ],
            [
              "JOL 3:11"
            ]
          ]
        },
        {
          "references": [
            [
              "000:02:20.960 --> 000:02:37.640"
            ],
            [
              "JOL 3:12"
            ]
          ]
        },
        {
          "references": [
            [
              "000:02:37.640 --> 000:02:56.080"
            ],
            [
              "JOL 3:13"
            ]
          ]
        },
        {
          "references": [
            [
              "000:02:56.080 --> 000:03:05.780"
            ],
            [
              "JOL 3:14"
            ]
          ]
        },
        {
          "references": [
            [
              "000:03:05.780 --> 000:03:13.680"
            ],
            [
              "JOL 3:15"
            ]
          ]
        },
        {
          "references": [
            [
              "000:03:13.680 --> 000:03:30.060"
            ],
            [
              "JOL 3:16"
            ]
          ]
        },
        {
          "references": [
            [
              "000:03:30.060 --> 000:03:47.300"
            ],
            [
              "JOL 3:17"
            ]
          ]
        },
        {
          "references": [
            [
              "000:03:47.300 --> 000:04:05.820"
            ],
            [
              "JOL 3:18"
            ]
          ]
        },
        {
          "references": [
            [
              "000:04:05.820 --> 000:04:20.140"
            ],
            [
              "JOL 3:19"
            ]
          ]
        },
        {
          "references": [
            [
              "000:04:20.140 --> 000:04:26.280"
            ],
            [
              "JOL 3:20"
            ]
          ]
        },
        {
          "references": [
            [
              "000:04:26.280 --> 000:04:35.560"
            ],
            [
              "JOL 3:21"
            ]
          ]
        }
      ]
    }
  ]
}